opengrapher/__init__.py
opengrapher-0.2.2.dist-info/LICENSE
opengrapher-0.2.2.dist-info/METADATA
opengrapher-0.2.2.dist-info/WHEEL
opengrapher-0.2.2.dist-info/entry_points.txt
opengrapher-0.2.2.dist-info/top_level.txt
opengrapher-0.2.2.dist-info/RECORD
