Metadata-Version: 2.1
Name: opengrapher
Version: 0.2.2
Summary: Utility for parsing the OpenGraph tags
Home-page: https://github.com/0rang3max/opengrapher
Author: Maxim Semenov
Author-email: 0rang3max@gmail.com
License: MIT
Download-URL: https://github.com/0rang3max/opengrapher/archive/v0.2.tar.gz
Keywords: opengraph
Platform: UNKNOWN
Classifier: Development Status :: 3 - Alpha
Classifier: Intended Audience :: Developers
Classifier: Topic :: Text Processing :: Markup :: HTML
Classifier: Topic :: Software Development :: Libraries :: Python Modules
Classifier: License :: OSI Approved :: MIT License
Classifier: Programming Language :: Python :: 3 :: Only
Requires-Python: >=3.4
Requires-Dist: beautifulsoup4
Requires-Dist: requests
